panos/__init__.py
panos/base.py
panos/device.py
panos/errors.py
panos/firewall.py
panos/ha.py
panos/network.py
panos/objects.py
panos/panorama.py
panos/plugins.py
panos/policies.py
panos/predefined.py
panos/updater.py
panos/userid.py
pan_os_python-1.12.3.dist-info/LICENSE
pan_os_python-1.12.3.dist-info/METADATA
pan_os_python-1.12.3.dist-info/WHEEL
pan_os_python-1.12.3.dist-info/RECORD
