Metadata-Version: 2.1
Name: pan-os-python
Version: 1.12.3
Summary: Framework for interacting with Palo Alto Networks devices via API
Home-page: https://github.com/PaloAltoNetworks/pan-os-python
License: ISC
Keywords: panos,pan-os-python
Author: Palo Alto Networks
Author-email: devrel@paloaltonetworks.com
Requires-Python: >=2.7, !=3.0.*, !=3.1.*, !=3.2.*, !=3.3.*, !=3.4.*
Classifier: Development Status :: 5 - Production/Stable
Classifier: Intended Audience :: Developers
Classifier: License :: OSI Approved
Classifier: License :: OSI Approved :: ISC License (ISCL)
Classifier: Natural Language :: English
Classifier: Programming Language :: Python :: 2
Classifier: Programming Language :: Python :: 2.7
Classifier: Programming Language :: Python :: 3
Classifier: Programming Language :: Python :: 3.5
Classifier: Programming Language :: Python :: 3.6
Classifier: Programming Language :: Python :: 3.7
Classifier: Programming Language :: Python :: 3.8
Classifier: Programming Language :: Python :: 3.9
Classifier: Programming Language :: Python :: 3.10
Classifier: Programming Language :: Python :: 3.11
Classifier: Programming Language :: Python :: 3.12
Requires-Dist: pan-python (>=0.17.0,<0.18.0)
Project-URL: Documentation, https://pan-os-python.readthedocs.io
Project-URL: Repository, https://github.com/PaloAltoNetworks/pan-os-python
